pensieve/EvaluationInput.py
pensieve/Memory.py
pensieve/Pensieve.py
pensieve/_PensieveWithoutDisplay.py
pensieve/__init__.py
pensieve/create_pensieve_function.py
pensieve/exceptions.py
pensieve/get_schedule.py
pensieve/get_type.py
pensieve/wrap_object.py
pensieve/tests/__init__.py
pensieve/tests/test_pensieve.py
pensieve-2022.4.20.1.dist-info/LICENSE
pensieve-2022.4.20.1.dist-info/METADATA
pensieve-2022.4.20.1.dist-info/WHEEL
pensieve-2022.4.20.1.dist-info/top_level.txt
pensieve-2022.4.20.1.dist-info/zip-safe
pensieve-2022.4.20.1.dist-info/RECORD
