Metadata-Version: 2.1
Name: pensieve
Version: 2022.4.20.1
Summary: Python library for organizing objects and dependencies in a graph structure
Home-page: https://github.com/idin/pensieve
Author: Idin
Author-email: py@idin.ca
License: MIT
Keywords: graph computation
Platform: UNKNOWN
Classifier: Development Status :: 3 - Alpha
Classifier: Intended Audience :: Developers
Classifier: Programming Language :: Python :: 3 :: Only
Classifier: Programming Language :: Python :: 3.6
Classifier: Programming Language :: Python :: 3.7
Classifier: Topic :: Software Development :: Libraries :: Python Modules
Requires-Python: ~=3.6
Requires-Dist: dill
Requires-Dist: toposort
Requires-Dist: disk
Requires-Dist: slytherin
Requires-Dist: chronometry
Requires-Dist: joblib
Requires-Dist: pandas
Requires-Dist: abstract (>=2022.4.20)
